image_crawl/__init__.py
image_crawl/src/__init__.py
image_crawl/src/collect.py
image_crawl/src/utils/__init__.py
image_crawl/src/utils/imageprocessor.py
image_crawl-0.1.dist-info/METADATA
image_crawl-0.1.dist-info/WHEEL
image_crawl-0.1.dist-info/entry_points.txt
image_crawl-0.1.dist-info/top_level.txt
image_crawl-0.1.dist-info/RECORD
