Metadata-Version: 2.1
Name: image-crawl
Version: 0.1
Summary: Crawl and transform images
Home-page: https://github.com/les-41-plats/image_crawl
Author: Les 41 Plats
Author-email: les41plats.work@gmail.com
License: MIT
Platform: UNKNOWN
Requires-Dist: anyio (==3.3.0)
Requires-Dist: appnope (==0.1.2)
Requires-Dist: argon2-cffi (==20.1.0)
Requires-Dist: astroid (==2.6.6)
Requires-Dist: async-generator (==1.10)
Requires-Dist: attrs (==21.2.0)
Requires-Dist: Babel (==2.9.1)
Requires-Dist: backcall (==0.2.0)
Requires-Dist: bleach (==4.0.0)
Requires-Dist: certifi (==2021.5.30)
Requires-Dist: cffi (==1.14.6)
Requires-Dist: charset-normalizer (==2.0.4)
Requires-Dist: cycler (==0.10.0)
Requires-Dist: debugpy (==1.4.1)
Requires-Dist: decorator (==5.0.9)
Requires-Dist: defusedxml (==0.7.1)
Requires-Dist: entrypoints (==0.3)
Requires-Dist: idna (==3.2)
Requires-Dist: ipykernel (==6.0.3)
Requires-Dist: ipython (==7.26.0)
Requires-Dist: ipython-genutils (==0.2.0)
Requires-Dist: isort (==5.9.3)
Requires-Dist: jedi (==0.18.0)
Requires-Dist: Jinja2 (==3.0.1)
Requires-Dist: json5 (==0.9.6)
Requires-Dist: jsonschema (==3.2.0)
Requires-Dist: jupyter-client (==6.1.12)
Requires-Dist: jupyter-core (==4.7.1)
Requires-Dist: jupyter-server (==1.10.2)
Requires-Dist: jupyterlab (==3.1.4)
Requires-Dist: jupyterlab-pygments (==0.1.2)
Requires-Dist: jupyterlab-server (==2.6.2)
Requires-Dist: kiwisolver (==1.3.1)
Requires-Dist: lazy-object-proxy (==1.6.0)
Requires-Dist: MarkupSafe (==2.0.1)
Requires-Dist: matplotlib (==3.4.2)
Requires-Dist: matplotlib-inline (==0.1.2)
Requires-Dist: mccabe (==0.6.1)
Requires-Dist: mistune (==0.8.4)
Requires-Dist: nbclassic (==0.3.1)
Requires-Dist: nbclient (==0.5.3)
Requires-Dist: nbconvert (==6.1.0)
Requires-Dist: nbformat (==5.1.3)
Requires-Dist: nest-asyncio (==1.5.1)
Requires-Dist: notebook (==6.4.1)
Requires-Dist: numpy (==1.21.1)
Requires-Dist: opencv-python (==4.5.3.56)
Requires-Dist: packaging (==21.0)
Requires-Dist: pandocfilters (==1.4.3)
Requires-Dist: parso (==0.8.2)
Requires-Dist: pexpect (==4.8.0)
Requires-Dist: pickleshare (==0.7.5)
Requires-Dist: Pillow (==8.3.1)
Requires-Dist: prometheus-client (==0.11.0)
Requires-Dist: prompt-toolkit (==3.0.19)
Requires-Dist: ptyprocess (==0.7.0)
Requires-Dist: pycparser (==2.20)
Requires-Dist: Pygments (==2.9.0)
Requires-Dist: pylint (==2.9.6)
Requires-Dist: pyparsing (==2.4.7)
Requires-Dist: pyrsistent (==0.18.0)
Requires-Dist: python-dateutil (==2.8.2)
Requires-Dist: pytz (==2021.1)
Requires-Dist: pyzmq (==22.2.1)
Requires-Dist: requests (==2.26.0)
Requires-Dist: requests-unixsocket (==0.2.0)
Requires-Dist: selenium (==3.141.0)
Requires-Dist: Send2Trash (==1.7.1)
Requires-Dist: six (==1.16.0)
Requires-Dist: sniffio (==1.2.0)
Requires-Dist: terminado (==0.10.1)
Requires-Dist: testpath (==0.5.0)
Requires-Dist: toml (==0.10.2)
Requires-Dist: tornado (==6.1)
Requires-Dist: traitlets (==5.0.5)
Requires-Dist: urllib3 (==1.26.6)
Requires-Dist: wcwidth (==0.2.5)
Requires-Dist: webencodings (==0.5.1)
Requires-Dist: websocket-client (==1.1.1)
Requires-Dist: wrapt (==1.12.1)
